{
  "courses": [
    {
      "name": "HTML và CSS",
      "description": "Để học web Front-end chúng ta luôn bắt đầu với ngôn ngữ HTML và CSS, đây là 2 ngôn ngữ có mặt trong mọi website trên internet.",
      "id": "1"
    },
    {
      "name": "JavaScript 2222",
      "description": "Với HTML, CSS bạn mới chỉ xây dựng được các websites tĩnh, chỉ bao gồm phần giao diện và gần như chưa có xử lý tương tác gì. Để thêm nhiều chức năng phong phú và tăng tính tương tác cho website bạn cần học Javascript.",
      "id": "2"
    },
    {
      "name": "CSS 2222222",
      "description": "Với HTML, CSS bạn mới chỉ xây dựng được các websites.",
      "id": "3"
    },
    {
      "id": "0127",
      "name": "HTML và CSS 222",
      "description": "Để học web Front-end chúng ta luôn bắt đầu với ngôn ngữ HTML và CSS, đây là 2 ngôn ngữ có mặt trong mọi website trên internet."
    },
    {
      "name": "HTML và CSS 333333333332222",
      "description": "Để học web Front-end",
      "id": "3005"
    }
  ]
}